setup.cfg
setup.py
cleanout/__init__.py
cleanout.egg-info/PKG-INFO
cleanout.egg-info/SOURCES.txt
cleanout.egg-info/dependency_links.txt
cleanout.egg-info/top_level.txt