Metadata-Version: 2.1
Name: cleanout
Version: 1.0
Summary: Library for clean screen of console
Home-page: UNKNOWN
Author-email: cklfgads@knowledgemd.com
License: UNKNOWN
Platform: UNKNOWN
